bytebomber/__init__.py
bytebomber/__main__.py
bytebomber-2.3.1.dist-info/licenses/LICENSE
bytebomber-2.3.1.dist-info/METADATA
bytebomber-2.3.1.dist-info/WHEEL
bytebomber-2.3.1.dist-info/entry_points.txt
bytebomber-2.3.1.dist-info/top_level.txt
bytebomber-2.3.1.dist-info/RECORD
