Metadata-Version: 2.4
Name: ByteBomber
Version: 2.3.1
Summary: ZIP bomb generator (for educational purposes only)
License: MIT
Project-URL: Source, https://github.com/redkitlab/ByteBomber
Project-URL: Documentation, https://github.com/redkitlab/ByteBomber/blob/main/README.md
Classifier: Programming Language :: Python :: 3
Classifier: License :: OSI Approved :: MIT License
Classifier: Operating System :: OS Independent
Classifier: Topic :: Security
Classifier: Topic :: Utilities
Classifier: Intended Audience :: Developers
Classifier: Intended Audience :: System Administrators
Classifier: Development Status :: 5 - Production/Stable
Requires-Python: <4.0,>=3.6
License-File: LICENSE
Dynamic: license-file
